llamaball/README.md
llamaball/__init__.py
llamaball/__main__.py
llamaball/cli.py
llamaball/core.py
llamaball/parsers.py
llamaball/utils.py
llamaball/web_server.py
llamaball/templates/base.html
llamaball/templates/chat.html
llamaball/templates/index.html
llamaball-1.1.1.dist-info/METADATA
llamaball-1.1.1.dist-info/WHEEL
llamaball-1.1.1.dist-info/entry_points.txt
llamaball-1.1.1.dist-info/licenses/LICENSE
llamaball-1.1.1.dist-info/RECORD
