Metadata-Version: 2.4
Name: llamaball
Version: 1.1.1
Summary: Accessible document chat and RAG system powered by Ollama
Project-URL: Homepage, https://github.com/coolhand/llamaball
Project-URL: Documentation, https://llamaball.readthedocs.io
Project-URL: Repository, https://github.com/coolhand/llamaball
Project-URL: Issues, https://github.com/coolhand/llamaball/issues
Project-URL: Changelog, https://github.com/coolhand/llamaball/blob/main/CHANGELOG.md
Author-email: Luke Steuber <luke@lukesteuber.com>
Maintainer-email: Luke Steuber <luke@lukesteuber.com>
License: MIT License
License-File: LICENSE
Keywords: accessibility,ai,cli,document-chat,embeddings,local-ai,ollama,rag
Classifier: Development Status :: 5 - Production/Stable
Classifier: Environment :: Console
Classifier: Intended Audience :: Developers
Classifier: Intended Audience :: End Users/Desktop
Classifier: License :: OSI Approved :: MIT License
Classifier: Operating System :: OS Independent
Classifier: Programming Language :: Python :: 3
Classifier: Programming Language :: Python :: 3.8
Classifier: Programming Language :: Python :: 3.9
Classifier: Programming Language :: Python :: 3.10
Classifier: Programming Language :: Python :: 3.11
Classifier: Programming Language :: Python :: 3.12
Classifier: Topic :: Scientific/Engineering :: Artificial Intelligence
Classifier: Topic :: Software Development :: Libraries :: Python Modules
Classifier: Topic :: Text Processing :: Indexing
Classifier: Topic :: Utilities
Classifier: Typing :: Typed
Requires-Python: >=3.8
Requires-Dist: beautifulsoup4>=4.9.0
Requires-Dist: markdown-it-py>=3.0.0
Requires-Dist: numpy>=1.21.0
Requires-Dist: ollama>=0.1.7
Requires-Dist: openpyxl>=3.1.0
Requires-Dist: pdfminer-six>=202010
Requires-Dist: prompt-toolkit>=3.0.0
Requires-Dist: pypandoc>=1.7.0
Requires-Dist: python-docx>=1.1.2
Requires-Dist: rich>=13.0.0
Requires-Dist: tiktoken>=0.5.0
Requires-Dist: tqdm>=4.64.0
Requires-Dist: typer[all]>=0.9.0
Requires-Dist: xlrd>=2.0.1
Provides-Extra: all
Requires-Dist: black>=23.0; extra == 'all'
Requires-Dist: isort>=5.0; extra == 'all'
Requires-Dist: memory-profiler>=0.61.0; extra == 'all'
Requires-Dist: mkdocs-material>=9.0.0; extra == 'all'
Requires-Dist: mkdocs>=1.5.0; extra == 'all'
Requires-Dist: mkdocstrings[python]>=0.20.0; extra == 'all'
Requires-Dist: mypy>=1.0; extra == 'all'
Requires-Dist: openpyxl>=3.1.0; extra == 'all'
Requires-Dist: pdfminer-six>=20221105; extra == 'all'
Requires-Dist: pre-commit>=3.0; extra == 'all'
Requires-Dist: psutil>=5.9.0; extra == 'all'
Requires-Dist: pytest-cov>=4.0; extra == 'all'
Requires-Dist: pytest>=7.0; extra == 'all'
Requires-Dist: python-docx>=0.8.11; extra == 'all'
Requires-Dist: xlrd>=2.0.1; extra == 'all'
Provides-Extra: dev
Requires-Dist: black>=23.0; extra == 'dev'
Requires-Dist: isort>=5.0; extra == 'dev'
Requires-Dist: mypy>=1.0; extra == 'dev'
Requires-Dist: pre-commit>=3.0; extra == 'dev'
Requires-Dist: pytest-cov>=4.0; extra == 'dev'
Requires-Dist: pytest>=7.0; extra == 'dev'
Provides-Extra: docs
Requires-Dist: mkdocs-material>=9.0.0; extra == 'docs'
Requires-Dist: mkdocs>=1.5.0; extra == 'docs'
Requires-Dist: mkdocstrings[python]>=0.20.0; extra == 'docs'
Provides-Extra: files
Requires-Dist: openpyxl>=3.1.0; extra == 'files'
Requires-Dist: pdfminer-six>=20221105; extra == 'files'
Requires-Dist: python-docx>=0.8.11; extra == 'files'
Requires-Dist: xlrd>=2.0.1; extra == 'files'
Provides-Extra: performance
Requires-Dist: memory-profiler>=0.61.0; extra == 'performance'
Requires-Dist: psutil>=5.9.0; extra == 'performance'
